{
  "doc_id": "synth-3e3693e89b71",
  "source_note": "Synth corpus v0.4.2-step0.1 template=professional_services bucket=clean seed=42004",
  "fields": [
    {
      "field_id": "vendor",
      "expected_value": "Beggan Chartered Accountants"
    },
    {
      "field_id": "total",
      "expected_value": 1652.26
    },
    {
      "field_id": "vat",
      "expected_value": 308.96
    },
    {
      "field_id": "date",
      "expected_value": "01/04/2026"
    },
    {
      "field_id": "subtotal",
      "expected_value": 1343.3
    },
    {
      "field_id": "vendor_country",
      "expected_value": "IE"
    }
  ]
}